gpt_function_decorator/__init__.py
gpt_function_decorator/generate_prompt.py
gpt_function_decorator/gpt_function.py
gpt_function_decorator-0.5.dist-info/LICENSE
gpt_function_decorator-0.5.dist-info/METADATA
gpt_function_decorator-0.5.dist-info/WHEEL
gpt_function_decorator-0.5.dist-info/top_level.txt
gpt_function_decorator-0.5.dist-info/RECORD
