Metadata-Version: 2.1
Name: gpt-function-decorator
Version: 0.5
Summary: Decorator to define GPT-powered functions
Author: Zulko
License: Apache-2.0
Project-URL: Homepage, https://github.com/zulko/gpt-function-decorator
Project-URL: Changelog, https://github.com/zulko/gpt-function-decorator/releases
Project-URL: Issues, https://github.com/zulko/gpt-function-decorator/issues
Project-URL: CI, https://github.com/zulko/gpt-function-decorator/actions
Classifier: License :: OSI Approved :: Apache Software License
Requires-Python: >=3.8
License-File: LICENSE
Requires-Dist: openai >=1.41
Requires-Dist: PyYAML
Provides-Extra: test
Requires-Dist: pytest ; extra == 'test'
